README.txt
setup.py
collective/__init__.py
collective.viewlet.links.egg-info/PKG-INFO
collective.viewlet.links.egg-info/SOURCES.txt
collective.viewlet.links.egg-info/dependency_links.txt
collective.viewlet.links.egg-info/entry_points.txt
collective.viewlet.links.egg-info/namespace_packages.txt
collective.viewlet.links.egg-info/not-zip-safe
collective.viewlet.links.egg-info/requires.txt
collective.viewlet.links.egg-info/top_level.txt
collective/viewlet/__init__.py
collective/viewlet/links/README.txt
collective/viewlet/links/TODO.txt
collective/viewlet/links/__init__.py
collective/viewlet/links/annotations.py
collective/viewlet/links/config.py
collective/viewlet/links/configure.zcml
collective/viewlet/links/interfaces.py
collective/viewlet/links/profiles.zcml
collective/viewlet/links/setuphandlers.py
collective/viewlet/links/Extensions/Install.py
collective/viewlet/links/Extensions/__init__.py
collective/viewlet/links/browser/__init__.py
collective/viewlet/links/browser/configure.zcml
collective/viewlet/links/browser/edit.py
collective/viewlet/links/browser/interfaces.py
collective/viewlet/links/browser/links_viewlet.pt
collective/viewlet/links/browser/viewlets.py
collective/viewlet/links/browser/stylesheets/style.css
collective/viewlet/links/locales/links-viewlet.pot
collective/viewlet/links/locales/manual.pot
collective/viewlet/links/locales/de/LC_MESSAGES/collective.viewlet.links.mo
collective/viewlet/links/locales/de/LC_MESSAGES/collective.viewlet.links.po
collective/viewlet/links/profiles/default/collective.viewlet.links_various.txt
collective/viewlet/links/profiles/default/cssregistry.xml
collective/viewlet/links/profiles/default/import_steps.xml
collective/viewlet/links/profiles/default/metadata.xml
collective/viewlet/links/profiles/default/rolemap.xml
collective/viewlet/links/profiles/default/viewlets.xml
collective/viewlet/links/tests/__init__.py
collective/viewlet/links/tests/base.py
collective/viewlet/links/tests/test_doctests.py
docs/HISTORY.txt
docs/INSTALL.txt
docs/LICENSE.GPL
docs/LICENSE.txt