Metadata-Version: 1.0
Name: collective.viewlet.links
Version: 0.2rc1
Summary: Viewlet displaying user-editable links on portal or folder level
Home-page: http://plone.org/products/collective.viewlet.links
Author: Liz Dahlstrom and Harald Friessnegger
Author-email: plone-developers@lists.sourceforge.net
License: GPL
Keywords: viewlet links
Platform: UNKNOWN
Classifier: Framework :: Plone
Classifier: Framework :: Zope2
Classifier: Framework :: Zope3
Classifier: Programming Language :: Python
Classifier: Topic :: Software Development :: Libraries :: Python Modules
